v_quantum_gate/__init__.py
v_quantum_gate/_version.py
v_quantum_gate/circuit.py
v_quantum_gate/decorators.py
v_quantum_gate/gate.py
v_quantum_gate/gateset.py
v_quantum_gate/parameter.py
v_quantum_gate/parametrized_circuit.py
v_quantum_gate/pauli.py
v_quantum_gate/typing.py
v_quantum_gate/utils.py
v_quantum_gate/vqe.py
v_quantum_gate/backends/__init__.py
v_quantum_gate/backends/_numba_backend_impl.py
v_quantum_gate/backends/backendbase.py
v_quantum_gate/backends/cusv.py
v_quantum_gate/backends/cutn.py
v_quantum_gate/backends/draw_backend.py
v_quantum_gate/backends/ibmq_backend.py
v_quantum_gate/backends/manyqubitgate_fallbacker.py
v_quantum_gate/backends/numba_backend.py
v_quantum_gate/backends/numpy_backend.py
v_quantum_gate/backends/onequbitgate_decomposer.py
v_quantum_gate/backends/onequbitgate_transpiler.py
v_quantum_gate/backends/qasm_output_backend.py
v_quantum_gate/backends/qasm_parser_backend_generator.py
v_quantum_gate/backends/quimb.py
v_quantum_gate/backends/sympy_backend.py
v_quantum_gate/backends/twoqubitgate_transpiler.py
v_quantum_gate/circuit_funcs/__init__.py
v_quantum_gate/circuit_funcs/circuit_to_unitary.py
v_quantum_gate/circuit_funcs/flatten.py
v_quantum_gate/circuit_funcs/json_serializer.py
v_quantum_gate/macros/__init__.py
v_quantum_gate-0.0.1.dist-info/LICENSE
v_quantum_gate-0.0.1.dist-info/METADATA
v_quantum_gate-0.0.1.dist-info/WHEEL
v_quantum_gate-0.0.1.dist-info/top_level.txt
v_quantum_gate-0.0.1.dist-info/RECORD
